django_flatblocks_xtd-0.2.dist-info/DESCRIPTION.rst
django_flatblocks_xtd-0.2.dist-info/METADATA
django_flatblocks_xtd-0.2.dist-info/metadata.json
django_flatblocks_xtd-0.2.dist-info/RECORD
django_flatblocks_xtd-0.2.dist-info/top_level.txt
django_flatblocks_xtd-0.2.dist-info/WHEEL
flatblocks_xtd/__init__.py
flatblocks_xtd/admin.py
flatblocks_xtd/forms.py
flatblocks_xtd/models.py
flatblocks_xtd/settings.py
flatblocks_xtd/tests.py
flatblocks_xtd/urls.py
flatblocks_xtd/views.py
flatblocks_xtd/locale/django.pot
flatblocks_xtd/locale/de/LC_MESSAGES/django.mo
flatblocks_xtd/locale/de/LC_MESSAGES/django.po
flatblocks_xtd/locale/hu/LC_MESSAGES/django.mo
flatblocks_xtd/locale/hu/LC_MESSAGES/django.po
flatblocks_xtd/locale/no/LC_MESSAGES/django.mo
flatblocks_xtd/locale/no/LC_MESSAGES/django.po
flatblocks_xtd/locale/ru/LC_MESSAGES/django.mo
flatblocks_xtd/locale/ru/LC_MESSAGES/django.po
flatblocks_xtd/management/__init__.py
flatblocks_xtd/management/commands/__init__.py
flatblocks_xtd/management/commands/createflatblock.py
flatblocks_xtd/management/commands/deleteflatblock.py
flatblocks_xtd/migrations/0001_initial.py
flatblocks_xtd/migrations/__init__.py
flatblocks_xtd/templates/flatblocks_xtd/edit.html
flatblocks_xtd/templates/flatblocks_xtd/flatblock_xtd.html
flatblocks_xtd/templatetags/__init__.py
flatblocks_xtd/templatetags/flatblock_xtd_tags.py
