Metadata-Version: 2.0
Name: django-flatblocks-xtd
Version: 0.2
Summary: django-flatblocks-xtd acts like django-flatblocks but adds support for markup content with django-markup and inline media content with django-inline-media.
Home-page: http://github.com/danirus/django-flatblocks-xtd/
Author: Daniel Rus Morales
Author-email: mbox@danir.us
License: New BSD License
Keywords: django apps
Platform: UNKNOWN
Classifier: Development Status :: 3 - Alpha
Classifier: Environment :: Plugins
Classifier: Framework :: Django
Classifier: Intended Audience :: Developers
Classifier: License :: OSI Approved :: BSD License
Classifier: Programming Language :: Python
Classifier: Topic :: Software Development :: Libraries :: Python Modules
